{
  "$schema": "http://cyclonedx.org/schema/bom-1.6.schema.json",
  "version": 1,
  "metadata": {
    "tools": [
      {
        "name": "trivy",
        "vendor": "aquasecurity",
        "version": "unknown"
      }
    ],
    "component": {
      "name": "centos",
      "purl": "pkg:oci/centos@centos7?digest=sha256:be65f488b7764ad3638f236b7b515b3678369a5124c47b8d32916d6487418ea4",
      "type": "library",
      "bom-ref": "pkg:oci/centos@centos7?digest=sha256:be65f488b7764ad3638f236b7b515b3678369a5124c47b8d32916d6487418ea4",
      "version": "centos7"
    },
    "timestamp": "2024-11-07T15:16:33.534369+00:00"
  },
  "bomFormat": "CycloneDX",
  "components": [
    {
      "name": "acl",
      "type": "library",
      "bom-ref": "BomRef.9683106869893632.3424927497040444",
      "version": "2.2.51-15.el7"
    },
    {
      "name": "audit-libs",
      "type": "library",
      "bom-ref": "BomRef.539435191342051.6789416876042998",
      "version": "2.8.5-4.el7"
    },
    {
      "name": "b2f7467f-b8f3-466d-8f34-d5902f6bd255",
      "type": "library",
      "bom-ref": "BomRef.057993642585890015.8648595561273664",
      "version": "unknown"
    },
    {
      "name": "basesystem",
      "type": "library",
      "bom-ref": "BomRef.07340813247072098.6402145831853399",
      "version": "10.0-7.el7.centos"
    },
    {
      "name": "bash",
      "type": "library",
      "bom-ref": "BomRef.12475269019461943.3212879832144697",
      "version": "4.2.46-34.el7"
    },
    {
      "name": "bc",
      "type": "library",
      "bom-ref": "BomRef.7125279895436061.2760218177244482",
      "version": "1.06.95-13.el7"
    },
    {
      "name": "bind-license",
      "type": "library",
      "bom-ref": "BomRef.6831752468118205.5447702736595869",
      "version": "32:9.11.4-26.P2.el7"
    },
    {
      "name": "binutils",
      "type": "library",
      "bom-ref": "BomRef.5059320559169913.5696504869807414",
      "version": "2.27-44.base.el7"
    },
    {
      "name": "bzip2-libs",
      "type": "library",
      "bom-ref": "BomRef.5723073320108568.2403056152901244",
      "version": "1.0.6-13.el7"
    },
    {
      "name": "ca-certificates",
      "type": "library",
      "bom-ref": "BomRef.3150762878689395.8752792954417918",
      "version": "2020.2.41-70.0.el7_8"
    },
    {
      "name": "centos",
      "type": "library",
      "bom-ref": "BomRef.13636069497244208.39483055158499936",
      "version": "7.9.2009"
    },
    {
      "name": "centos-release",
      "type": "library",
      "bom-ref": "BomRef.5864308457377085.6237741792083524",
      "version": "7-9.2009.0.el7.centos"
    },
    {
      "name": "chkconfig",
      "type": "library",
      "bom-ref": "BomRef.5109353503070917.5248556956929712",
      "version": "1.7.6-1.el7"
    },
    {
      "name": "coreutils",
      "type": "library",
      "bom-ref": "BomRef.5913696198156015.8449313250101518",
      "version": "8.22-24.el7"
    },
    {
      "name": "cpio",
      "type": "library",
      "bom-ref": "BomRef.9753508332280654.8546833527374805",
      "version": "2.11-28.el7"
    },
    {
      "name": "cracklib",
      "type": "library",
      "bom-ref": "BomRef.07975902054800499.0715601581897517",
      "version": "2.9.0-11.el7"
    },
    {
      "name": "cracklib-dicts",
      "type": "library",
      "bom-ref": "BomRef.09113560809499521.2962365642235617",
      "version": "2.9.0-11.el7"
    },
    {
      "name": "cryptsetup-libs",
      "type": "library",
      "bom-ref": "BomRef.41636622275731816.2927520489871589",
      "version": "2.0.3-6.el7"
    },
    {
      "name": "curl",
      "type": "library",
      "bom-ref": "BomRef.062012191817703344.49266122826585734",
      "version": "7.29.0-59.el7"
    },
    {
      "name": "cyrus-sasl-lib",
      "type": "library",
      "bom-ref": "BomRef.6116128301474562.5137638303318507",
      "version": "2.1.26-23.el7"
    },
    {
      "name": "dbus",
      "type": "library",
      "bom-ref": "BomRef.8205015268929786.183534747464705",
      "version": "1:1.10.24-15.el7"
    },
    {
      "name": "dbus-glib",
      "type": "library",
      "bom-ref": "BomRef.7674203601626399.9727872167600088",
      "version": "0.100-7.el7"
    },
    {
      "name": "dbus-libs",
      "type": "library",
      "bom-ref": "BomRef.07254756197213386.8921284996085548",
      "version": "1:1.10.24-15.el7"
    },
    {
      "name": "dbus-python",
      "type": "library",
      "bom-ref": "BomRef.787705607814047.1434286330258584",
      "version": "1.1.1-9.el7"
    },
    {
      "name": "device-mapper",
      "type": "library",
      "bom-ref": "BomRef.36461515723031634.293704901061269",
      "version": "7:1.02.170-6.el7"
    },
    {
      "name": "device-mapper-libs",
      "type": "library",
      "bom-ref": "BomRef.5953159827034046.7822423402553327",
      "version": "7:1.02.170-6.el7"
    },
    {
      "name": "diffutils",
      "type": "library",
      "bom-ref": "BomRef.3646529792904001.5241600812988473",
      "version": "3.3-5.el7"
    },
    {
      "name": "dracut",
      "type": "library",
      "bom-ref": "BomRef.49466594038274503.1309141083579034",
      "version": "033-572.el7"
    },
    {
      "name": "elfutils-default-yama-scope",
      "type": "library",
      "bom-ref": "BomRef.6836486802262614.25751389504214217",
      "version": "0.176-5.el7"
    },
    {
      "name": "elfutils-libelf",
      "type": "library",
      "bom-ref": "BomRef.6150835749142108.2381819414441554",
      "version": "0.176-5.el7"
    },
    {
      "name": "elfutils-libs",
      "type": "library",
      "bom-ref": "BomRef.09413730679177457.4453167340081914",
      "version": "0.176-5.el7"
    },
    {
      "name": "expat",
      "type": "library",
      "bom-ref": "BomRef.9618140028265427.2169137474651106",
      "version": "2.1.0-12.el7"
    },
    {
      "name": "file-libs",
      "type": "library",
      "bom-ref": "BomRef.24210165143682427.9108332345109941",
      "version": "5.11-37.el7"
    },
    {
      "name": "filesystem",
      "type": "library",
      "bom-ref": "BomRef.47124791204602146.022754232683465214",
      "version": "3.2-25.el7"
    },
    {
      "name": "findutils",
      "type": "library",
      "bom-ref": "BomRef.8741829368758849.814930948589656",
      "version": "1:4.5.11-6.el7"
    },
    {
      "name": "gawk",
      "type": "library",
      "bom-ref": "BomRef.858489408490906.8276266839955646",
      "version": "4.0.2-4.el7_3.1"
    },
    {
      "name": "gdbm",
      "type": "library",
      "bom-ref": "BomRef.06004104628966789.7771052277891227",
      "version": "1.10-8.el7"
    },
    {
      "name": "geoipupdate",
      "type": "library",
      "bom-ref": "BomRef.5446205429261812.25444310735587283",
      "version": "2.5.0-1.el7"
    },
    {
      "name": "glib2",
      "type": "library",
      "bom-ref": "BomRef.7029648021955753.14255122510509988",
      "version": "2.56.1-7.el7"
    },
    {
      "name": "glibc",
      "type": "library",
      "bom-ref": "BomRef.8860082289666387.5848918898529945",
      "version": "2.17-317.el7"
    },
    {
      "name": "glibc-common",
      "type": "library",
      "bom-ref": "BomRef.4937757936815731.18289289591076663",
      "version": "2.17-317.el7"
    },
    {
      "name": "gmp",
      "type": "library",
      "bom-ref": "BomRef.11171634813927067.82634141896032",
      "version": "1:6.0.0-15.el7"
    },
    {
      "name": "gnupg2",
      "type": "library",
      "bom-ref": "BomRef.5846763080850081.1625501928426374",
      "version": "2.0.22-5.el7_5"
    },
    {
      "name": "gobject-introspection",
      "type": "library",
      "bom-ref": "BomRef.866456653526203.3383387341769639",
      "version": "1.56.1-1.el7"
    },
    {
      "name": "gpgme",
      "type": "library",
      "bom-ref": "BomRef.9486471790935657.4507243341174476",
      "version": "1.3.2-5.el7"
    },
    {
      "name": "grep",
      "type": "library",
      "bom-ref": "BomRef.5728937023185666.38834239825823647",
      "version": "2.20-3.el7"
    },
    {
      "name": "gzip",
      "type": "library",
      "bom-ref": "BomRef.5653505824121918.790616916094003",
      "version": "1.5-10.el7"
    },
    {
      "name": "hardlink",
      "type": "library",
      "bom-ref": "BomRef.20573920132313772.045865452663179984",
      "version": "1:1.0-19.el7"
    },
    {
      "name": "hostname",
      "type": "library",
      "bom-ref": "BomRef.6153753672433462.3422356156836608",
      "version": "3.13-3.el7_7.1"
    },
    {
      "name": "info",
      "type": "library",
      "bom-ref": "BomRef.8573261232617271.9688087109544156",
      "version": "5.1-5.el7"
    },
    {
      "name": "iputils",
      "type": "library",
      "bom-ref": "BomRef.24420921802104023.1381599731786386",
      "version": "20160308-10.el7"
    },
    {
      "name": "json-c",
      "type": "library",
      "bom-ref": "BomRef.7029191718117426.7209543357355848",
      "version": "0.11-4.el7_0"
    },
    {
      "name": "keyutils-libs",
      "type": "library",
      "bom-ref": "BomRef.24490850502155437.3040958434951938",
      "version": "1.5.8-3.el7"
    },
    {
      "name": "kmod",
      "type": "library",
      "bom-ref": "BomRef.5090672853874949.16367635762569388",
      "version": "20-28.el7"
    },
    {
      "name": "kmod-libs",
      "type": "library",
      "bom-ref": "BomRef.17746955210333426.5749307672306114",
      "version": "20-28.el7"
    },
    {
      "name": "kpartx",
      "type": "library",
      "bom-ref": "BomRef.22438930016266323.43826084523368014",
      "version": "0.4.9-133.el7"
    },
    {
      "name": "krb5-libs",
      "type": "library",
      "bom-ref": "BomRef.7477949854509315.6201581286294816",
      "version": "1.15.1-50.el7"
    },
    {
      "name": "libacl",
      "type": "library",
      "bom-ref": "BomRef.27386252363697694.847335820761125",
      "version": "2.2.51-15.el7"
    },
    {
      "name": "libassuan",
      "type": "library",
      "bom-ref": "BomRef.1693092195767828.019978008897911237",
      "version": "2.1.0-3.el7"
    },
    {
      "name": "libattr",
      "type": "library",
      "bom-ref": "BomRef.18674425310107823.35173353574053123",
      "version": "2.4.46-13.el7"
    },
    {
      "name": "libblkid",
      "type": "library",
      "bom-ref": "BomRef.08215801946931423.6589235676874919",
      "version": "2.23.2-65.el7"
    },
    {
      "name": "libcap",
      "type": "library",
      "bom-ref": "BomRef.9964725481371729.7597031503293974",
      "version": "2.22-11.el7"
    },
    {
      "name": "libcap-ng",
      "type": "library",
      "bom-ref": "BomRef.8227145822190692.0592663437373141",
      "version": "0.7.5-4.el7"
    },
    {
      "name": "libcom_err",
      "type": "library",
      "bom-ref": "BomRef.7934058889047312.37028885631583064",
      "version": "1.42.9-19.el7"
    },
    {
      "name": "libcurl",
      "type": "library",
      "bom-ref": "BomRef.9444124999510763.9457027069583186",
      "version": "7.29.0-59.el7"
    },
    {
      "name": "libdb",
      "type": "library",
      "bom-ref": "BomRef.5329346635326255.31705414342563387",
      "version": "5.3.21-25.el7"
    },
    {
      "name": "libdb-utils",
      "type": "library",
      "bom-ref": "BomRef.5366295419133734.6873977434381618",
      "version": "5.3.21-25.el7"
    },
    {
      "name": "libffi",
      "type": "library",
      "bom-ref": "BomRef.1513977447794428.8389650225127179",
      "version": "3.0.13-19.el7"
    },
    {
      "name": "libgcc",
      "type": "library",
      "bom-ref": "BomRef.5469124038901767.4473383928224298",
      "version": "4.8.5-44.el7"
    },
    {
      "name": "libgcrypt",
      "type": "library",
      "bom-ref": "BomRef.10938756009552597.3300926576881079",
      "version": "1.5.3-14.el7"
    },
    {
      "name": "libgpg-error",
      "type": "library",
      "bom-ref": "BomRef.06646288548750612.07838253227117487",
      "version": "1.12-3.el7"
    },
    {
      "name": "libidn",
      "type": "library",
      "bom-ref": "BomRef.9445395981460681.608128563656574",
      "version": "1.28-4.el7"
    },
    {
      "name": "libmount",
      "type": "library",
      "bom-ref": "BomRef.8217329453660381.8165448139837509",
      "version": "2.23.2-65.el7"
    },
    {
      "name": "libpwquality",
      "type": "library",
      "bom-ref": "BomRef.24260073883923405.546150904731525",
      "version": "1.2.3-5.el7"
    },
    {
      "name": "libselinux",
      "type": "library",
      "bom-ref": "BomRef.4874455545363099.11617780514507492",
      "version": "2.5-15.el7"
    },
    {
      "name": "libsemanage",
      "type": "library",
      "bom-ref": "BomRef.15616968553881716.7404580637378142",
      "version": "2.5-14.el7"
    },
    {
      "name": "libsepol",
      "type": "library",
      "bom-ref": "BomRef.015251285026084083.5726410217003062",
      "version": "2.5-10.el7"
    },
    {
      "name": "libsmartcols",
      "type": "library",
      "bom-ref": "BomRef.717600150965402.4877125536037026",
      "version": "2.23.2-65.el7"
    },
    {
      "name": "libssh2",
      "type": "library",
      "bom-ref": "BomRef.32595213010467894.06452079515891507",
      "version": "1.8.0-4.el7"
    },
    {
      "name": "libstdc++",
      "type": "library",
      "bom-ref": "BomRef.44007338279434693.4187647255009058",
      "version": "4.8.5-44.el7"
    },
    {
      "name": "libtasn1",
      "type": "library",
      "bom-ref": "BomRef.8322828539792391.6127615308386836",
      "version": "4.10-1.el7"
    },
    {
      "name": "libuser",
      "type": "library",
      "bom-ref": "BomRef.932244932007372.5094787502399755",
      "version": "0.60-9.el7"
    },
    {
      "name": "libutempter",
      "type": "library",
      "bom-ref": "BomRef.5132157465737628.11295308206024446",
      "version": "1.1.6-4.el7"
    },
    {
      "name": "libuuid",
      "type": "library",
      "bom-ref": "BomRef.6594620275851222.05320409431023021",
      "version": "2.23.2-65.el7"
    },
    {
      "name": "libverto",
      "type": "library",
      "bom-ref": "BomRef.911844940654492.26190724416344946",
      "version": "0.2.5-4.el7"
    },
    {
      "name": "libxml2",
      "type": "library",
      "bom-ref": "BomRef.15176843369108717.2893853154979652",
      "version": "2.9.1-6.el7.5"
    },
    {
      "name": "libxml2-python",
      "type": "library",
      "bom-ref": "BomRef.28372242487914245.13604827176414314",
      "version": "2.9.1-6.el7.5"
    },
    {
      "name": "lua",
      "type": "library",
      "bom-ref": "BomRef.27662145177673214.12674095952041053",
      "version": "5.1.4-15.el7"
    },
    {
      "name": "lz4",
      "type": "library",
      "bom-ref": "BomRef.2546109420421333.6392284422259783",
      "version": "1.8.3-1.el7"
    },
    {
      "name": "ncurses",
      "type": "library",
      "bom-ref": "BomRef.4388463302713367.970790864615222",
      "version": "5.9-14.20130511.el7_4"
    },
    {
      "name": "ncurses-base",
      "type": "library",
      "bom-ref": "BomRef.10430400278672225.24309525057334458",
      "version": "5.9-14.20130511.el7_4"
    },
    {
      "name": "ncurses-libs",
      "type": "library",
      "bom-ref": "BomRef.48712102028002324.4129004970298864",
      "version": "5.9-14.20130511.el7_4"
    },
    {
      "name": "nspr",
      "type": "library",
      "bom-ref": "BomRef.2976489159076232.4208212013443531",
      "version": "4.25.0-2.el7_9"
    },
    {
      "name": "nss",
      "type": "library",
      "bom-ref": "BomRef.782229008402026.14648781281129208",
      "version": "3.53.1-3.el7_9"
    },
    {
      "name": "nss-pem",
      "type": "library",
      "bom-ref": "BomRef.8311951174030063.79694477790273",
      "version": "1.0.3-7.el7"
    },
    {
      "name": "nss-softokn",
      "type": "library",
      "bom-ref": "BomRef.882540142010189.6294100739401446",
      "version": "3.53.1-6.el7_9"
    },
    {
      "name": "nss-softokn-freebl",
      "type": "library",
      "bom-ref": "BomRef.5708818034221129.3804378761299618",
      "version": "3.53.1-6.el7_9"
    },
    {
      "name": "nss-sysinit",
      "type": "library",
      "bom-ref": "BomRef.36652782843032217.6956634453410063",
      "version": "3.53.1-3.el7_9"
    },
    {
      "name": "nss-tools",
      "type": "library",
      "bom-ref": "BomRef.3570620169721105.8971833638785001",
      "version": "3.53.1-3.el7_9"
    },
    {
      "name": "nss-util",
      "type": "library",
      "bom-ref": "BomRef.2829694193449187.5877812480589429",
      "version": "3.53.1-1.el7_9"
    },
    {
      "name": "openldap",
      "type": "library",
      "bom-ref": "BomRef.27794806826922025.017531516503773492",
      "version": "2.4.44-22.el7"
    },
    {
      "name": "openssl-libs",
      "type": "library",
      "bom-ref": "BomRef.5447581939640517.3470870648769323",
      "version": "1:1.0.2k-19.el7"
    },
    {
      "name": "p11-kit",
      "type": "library",
      "bom-ref": "BomRef.11543822035669848.3931458759652209",
      "version": "0.23.5-3.el7"
    },
    {
      "name": "p11-kit-trust",
      "type": "library",
      "bom-ref": "BomRef.9957289304301511.4949770751840835",
      "version": "0.23.5-3.el7"
    },
    {
      "name": "pam",
      "type": "library",
      "bom-ref": "BomRef.31180001514978517.7973680439293804",
      "version": "1.1.8-23.el7"
    },
    {
      "name": "passwd",
      "type": "library",
      "bom-ref": "BomRef.8322931822907467.37110848756323567",
      "version": "0.79-6.el7"
    },
    {
      "name": "pcre",
      "type": "library",
      "bom-ref": "BomRef.6143491786106843.362568875709669",
      "version": "8.32-17.el7"
    },
    {
      "name": "pinentry",
      "type": "library",
      "bom-ref": "BomRef.024488909026581185.11597685871456509",
      "version": "0.8.1-17.el7"
    },
    {
      "name": "pkg:oci/centos@sha256%3Abe65f488b7764ad3638f236b7b515b3678369a5124c47b8d32916d6487418ea4?arch=amd64&repository_url=index.docker.io%2Flibrary%2Fcentos",
      "type": "library",
      "bom-ref": "BomRef.3324682176988484.6116024106049724",
      "version": "unknown"
    },
    {
      "name": "pkg:rpm/centos/acl@2.2.51-15.el7?arch=x86_64&distro=centos-7.9.2009",
      "type": "library",
      "bom-ref": "BomRef.8482080066185224.10958285108431443",
      "version": "unknown"
    },
    {
      "name": "pkg:rpm/centos/audit-libs@2.8.5-4.el7?arch=x86_64&distro=centos-7.9.2009",
      "type": "library",
      "bom-ref": "BomRef.09646571441629337.15215251842763444",
      "version": "unknown"
    },
    {
      "name": "pkg:rpm/centos/basesystem@10.0-7.el7.centos?arch=noarch&distro=centos-7.9.2009",
      "type": "library",
      "bom-ref": "BomRef.04053329806906536.42725921623339147",
      "version": "unknown"
    },
    {
      "name": "pkg:rpm/centos/bash@4.2.46-34.el7?arch=x86_64&distro=centos-7.9.2009",
      "type": "library",
      "bom-ref": "BomRef.7134131471678684.7889429814817616",
      "version": "unknown"
    },
    {
      "name": "pkg:rpm/centos/bc@1.06.95-13.el7?arch=x86_64&distro=centos-7.9.2009",
      "type": "library",
      "bom-ref": "BomRef.33857822218813316.7552305384093357",
      "version": "unknown"
    },
    {
      "name": "pkg:rpm/centos/bind-license@9.11.4-26.P2.el7?arch=noarch&distro=centos-7.9.2009&epoch=32",
      "type": "library",
      "bom-ref": "BomRef.6031860677211648.3239693754658175",
      "version": "unknown"
    },
    {
      "name": "pkg:rpm/centos/binutils@2.27-44.base.el7?arch=x86_64&distro=centos-7.9.2009",
      "type": "library",
      "bom-ref": "BomRef.02183064099084342.566083058802005",
      "version": "unknown"
    },
    {
      "name": "pkg:rpm/centos/bzip2-libs@1.0.6-13.el7?arch=x86_64&distro=centos-7.9.2009",
      "type": "library",
      "bom-ref": "BomRef.45487917549634593.4177623362994095",
      "version": "unknown"
    },
    {
      "name": "pkg:rpm/centos/ca-certificates@2020.2.41-70.0.el7_8?arch=noarch&distro=centos-7.9.2009",
      "type": "library",
      "bom-ref": "BomRef.6715443298626859.6217813837827428",
      "version": "unknown"
    },
    {
      "name": "pkg:rpm/centos/centos-release@7-9.2009.0.el7.centos?arch=x86_64&distro=centos-7.9.2009",
      "type": "library",
      "bom-ref": "BomRef.46902099014219756.6491639247271938",
      "version": "unknown"
    },
    {
      "name": "pkg:rpm/centos/chkconfig@1.7.6-1.el7?arch=x86_64&distro=centos-7.9.2009",
      "type": "library",
      "bom-ref": "BomRef.38197213244674333.38584593667802947",
      "version": "unknown"
    },
    {
      "name": "pkg:rpm/centos/coreutils@8.22-24.el7?arch=x86_64&distro=centos-7.9.2009",
      "type": "library",
      "bom-ref": "BomRef.7111467413978058.506607624759521",
      "version": "unknown"
    },
    {
      "name": "pkg:rpm/centos/cpio@2.11-28.el7?arch=x86_64&distro=centos-7.9.2009",
      "type": "library",
      "bom-ref": "BomRef.6112987920128037.21125736682874563",
      "version": "unknown"
    },
    {
      "name": "pkg:rpm/centos/cracklib-dicts@2.9.0-11.el7?arch=x86_64&distro=centos-7.9.2009",
      "type": "library",
      "bom-ref": "BomRef.3784304008894782.5118519880466966",
      "version": "unknown"
    },
    {
      "name": "pkg:rpm/centos/cracklib@2.9.0-11.el7?arch=x86_64&distro=centos-7.9.2009",
      "type": "library",
      "bom-ref": "BomRef.4888581320832842.3539499570520953",
      "version": "unknown"
    },
    {
      "name": "pkg:rpm/centos/cryptsetup-libs@2.0.3-6.el7?arch=x86_64&distro=centos-7.9.2009",
      "type": "library",
      "bom-ref": "BomRef.8296968833052679.34668572699676536",
      "version": "unknown"
    },
    {
      "name": "pkg:rpm/centos/curl@7.29.0-59.el7?arch=x86_64&distro=centos-7.9.2009",
      "type": "library",
      "bom-ref": "BomRef.10978319758943689.9304933730628435",
      "version": "unknown"
    },
    {
      "name": "pkg:rpm/centos/cyrus-sasl-lib@2.1.26-23.el7?arch=x86_64&distro=centos-7.9.2009",
      "type": "library",
      "bom-ref": "BomRef.08414766719086875.8459684995663234",
      "version": "unknown"
    },
    {
      "name": "pkg:rpm/centos/dbus-glib@0.100-7.el7?arch=x86_64&distro=centos-7.9.2009",
      "type": "library",
      "bom-ref": "BomRef.7603726149683712.44842367717705334",
      "version": "unknown"
    },
    {
      "name": "pkg:rpm/centos/dbus-libs@1.10.24-15.el7?arch=x86_64&distro=centos-7.9.2009&epoch=1",
      "type": "library",
      "bom-ref": "BomRef.6241981551378307.24462842266975637",
      "version": "unknown"
    },
    {
      "name": "pkg:rpm/centos/dbus-python@1.1.1-9.el7?arch=x86_64&distro=centos-7.9.2009",
      "type": "library",
      "bom-ref": "BomRef.805817690117059.980527669909242",
      "version": "unknown"
    },
    {
      "name": "pkg:rpm/centos/dbus@1.10.24-15.el7?arch=x86_64&distro=centos-7.9.2009&epoch=1",
      "type": "library",
      "bom-ref": "BomRef.2177583145952482.2085145602198637",
      "version": "unknown"
    },
    {
      "name": "pkg:rpm/centos/device-mapper-libs@1.02.170-6.el7?arch=x86_64&distro=centos-7.9.2009&epoch=7",
      "type": "library",
      "bom-ref": "BomRef.757285176615639.30079946128356727",
      "version": "unknown"
    },
    {
      "name": "pkg:rpm/centos/device-mapper@1.02.170-6.el7?arch=x86_64&distro=centos-7.9.2009&epoch=7",
      "type": "library",
      "bom-ref": "BomRef.0500009078605308.16525287386835474",
      "version": "unknown"
    },
    {
      "name": "pkg:rpm/centos/diffutils@3.3-5.el7?arch=x86_64&distro=centos-7.9.2009",
      "type": "library",
      "bom-ref": "BomRef.7410904425378922.8150480979104315",
      "version": "unknown"
    },
    {
      "name": "pkg:rpm/centos/dracut@033-572.el7?arch=x86_64&distro=centos-7.9.2009",
      "type": "library",
      "bom-ref": "BomRef.7250010128803137.2666620096170671",
      "version": "unknown"
    },
    {
      "name": "pkg:rpm/centos/elfutils-default-yama-scope@0.176-5.el7?arch=noarch&distro=centos-7.9.2009",
      "type": "library",
      "bom-ref": "BomRef.1280962955337872.6380582352989193",
      "version": "unknown"
    },
    {
      "name": "pkg:rpm/centos/elfutils-libelf@0.176-5.el7?arch=x86_64&distro=centos-7.9.2009",
      "type": "library",
      "bom-ref": "BomRef.3585567576707819.9319653832146283",
      "version": "unknown"
    },
    {
      "name": "pkg:rpm/centos/elfutils-libs@0.176-5.el7?arch=x86_64&distro=centos-7.9.2009",
      "type": "library",
      "bom-ref": "BomRef.6218149150985431.3039539087537433",
      "version": "unknown"
    },
    {
      "name": "pkg:rpm/centos/expat@2.1.0-12.el7?arch=x86_64&distro=centos-7.9.2009",
      "type": "library",
      "bom-ref": "BomRef.2370556436538903.22947977889555993",
      "version": "unknown"
    },
    {
      "name": "pkg:rpm/centos/file-libs@5.11-37.el7?arch=x86_64&distro=centos-7.9.2009",
      "type": "library",
      "bom-ref": "BomRef.6332229786811459.8819197214733189",
      "version": "unknown"
    },
    {
      "name": "pkg:rpm/centos/filesystem@3.2-25.el7?arch=x86_64&distro=centos-7.9.2009",
      "type": "library",
      "bom-ref": "BomRef.6249323781848204.2800542636206207",
      "version": "unknown"
    },
    {
      "name": "pkg:rpm/centos/findutils@4.5.11-6.el7?arch=x86_64&distro=centos-7.9.2009&epoch=1",
      "type": "library",
      "bom-ref": "BomRef.1535708737125726.9851514921168668",
      "version": "unknown"
    },
    {
      "name": "pkg:rpm/centos/gawk@4.0.2-4.el7_3.1?arch=x86_64&distro=centos-7.9.2009",
      "type": "library",
      "bom-ref": "BomRef.4578503510904596.6764302156482087",
      "version": "unknown"
    },
    {
      "name": "pkg:rpm/centos/gdbm@1.10-8.el7?arch=x86_64&distro=centos-7.9.2009",
      "type": "library",
      "bom-ref": "BomRef.8789965874274014.0549419345103106",
      "version": "unknown"
    },
    {
      "name": "pkg:rpm/centos/geoipupdate@2.5.0-1.el7?arch=x86_64&distro=centos-7.9.2009",
      "type": "library",
      "bom-ref": "BomRef.6266479496990721.6755247596276939",
      "version": "unknown"
    },
    {
      "name": "pkg:rpm/centos/glib2@2.56.1-7.el7?arch=x86_64&distro=centos-7.9.2009",
      "type": "library",
      "bom-ref": "BomRef.663987839268528.04752075229213937",
      "version": "unknown"
    },
    {
      "name": "pkg:rpm/centos/glibc-common@2.17-317.el7?arch=x86_64&distro=centos-7.9.2009",
      "type": "library",
      "bom-ref": "BomRef.8406906183661705.17813406204012705",
      "version": "unknown"
    },
    {
      "name": "pkg:rpm/centos/glibc@2.17-317.el7?arch=x86_64&distro=centos-7.9.2009",
      "type": "library",
      "bom-ref": "BomRef.6410873741070992.036857118978913195",
      "version": "unknown"
    },
    {
      "name": "pkg:rpm/centos/gmp@6.0.0-15.el7?arch=x86_64&distro=centos-7.9.2009&epoch=1",
      "type": "library",
      "bom-ref": "BomRef.44172163091307226.4004541134644547",
      "version": "unknown"
    },
    {
      "name": "pkg:rpm/centos/gnupg2@2.0.22-5.el7_5?arch=x86_64&distro=centos-7.9.2009",
      "type": "library",
      "bom-ref": "BomRef.989883659417556.9319636192227638",
      "version": "unknown"
    },
    {
      "name": "pkg:rpm/centos/gobject-introspection@1.56.1-1.el7?arch=x86_64&distro=centos-7.9.2009",
      "type": "library",
      "bom-ref": "BomRef.30571853313711084.4460882537765475",
      "version": "unknown"
    },
    {
      "name": "pkg:rpm/centos/gpgme@1.3.2-5.el7?arch=x86_64&distro=centos-7.9.2009",
      "type": "library",
      "bom-ref": "BomRef.10248628051791409.5040119349763146",
      "version": "unknown"
    },
    {
      "name": "pkg:rpm/centos/grep@2.20-3.el7?arch=x86_64&distro=centos-7.9.2009",
      "type": "library",
      "bom-ref": "BomRef.6194425528485259.33842079640205003",
      "version": "unknown"
    },
    {
      "name": "pkg:rpm/centos/gzip@1.5-10.el7?arch=x86_64&distro=centos-7.9.2009",
      "type": "library",
      "bom-ref": "BomRef.8126181861988361.41434738507603197",
      "version": "unknown"
    },
    {
      "name": "pkg:rpm/centos/hardlink@1.0-19.el7?arch=x86_64&distro=centos-7.9.2009&epoch=1",
      "type": "library",
      "bom-ref": "BomRef.7869926598497546.018128985081250604",
      "version": "unknown"
    },
    {
      "name": "pkg:rpm/centos/hostname@3.13-3.el7_7.1?arch=x86_64&distro=centos-7.9.2009",
      "type": "library",
      "bom-ref": "BomRef.3821354631203039.10719869032732732",
      "version": "unknown"
    },
    {
      "name": "pkg:rpm/centos/info@5.1-5.el7?arch=x86_64&distro=centos-7.9.2009",
      "type": "library",
      "bom-ref": "BomRef.24519108893793717.11547544648482422",
      "version": "unknown"
    },
    {
      "name": "pkg:rpm/centos/iputils@20160308-10.el7?arch=x86_64&distro=centos-7.9.2009",
      "type": "library",
      "bom-ref": "BomRef.6547913237021074.33136721587494666",
      "version": "unknown"
    },
    {
      "name": "pkg:rpm/centos/json-c@0.11-4.el7_0?arch=x86_64&distro=centos-7.9.2009",
      "type": "library",
      "bom-ref": "BomRef.6072262996782428.5145314283773903",
      "version": "unknown"
    },
    {
      "name": "pkg:rpm/centos/keyutils-libs@1.5.8-3.el7?arch=x86_64&distro=centos-7.9.2009",
      "type": "library",
      "bom-ref": "BomRef.07738674078897034.5919048846959302",
      "version": "unknown"
    },
    {
      "name": "pkg:rpm/centos/kmod-libs@20-28.el7?arch=x86_64&distro=centos-7.9.2009",
      "type": "library",
      "bom-ref": "BomRef.9054974962289634.501556331610808",
      "version": "unknown"
    },
    {
      "name": "pkg:rpm/centos/kmod@20-28.el7?arch=x86_64&distro=centos-7.9.2009",
      "type": "library",
      "bom-ref": "BomRef.05398672634921997.7650355545711406",
      "version": "unknown"
    },
    {
      "name": "pkg:rpm/centos/kpartx@0.4.9-133.el7?arch=x86_64&distro=centos-7.9.2009",
      "type": "library",
      "bom-ref": "BomRef.6610941716539932.2687495826670516",
      "version": "unknown"
    },
    {
      "name": "pkg:rpm/centos/krb5-libs@1.15.1-50.el7?arch=x86_64&distro=centos-7.9.2009",
      "type": "library",
      "bom-ref": "BomRef.26407949568515654.6908314029997384",
      "version": "unknown"
    },
    {
      "name": "pkg:rpm/centos/libacl@2.2.51-15.el7?arch=x86_64&distro=centos-7.9.2009",
      "type": "library",
      "bom-ref": "BomRef.9170892163702018.5490025919519991",
      "version": "unknown"
    },
    {
      "name": "pkg:rpm/centos/libassuan@2.1.0-3.el7?arch=x86_64&distro=centos-7.9.2009",
      "type": "library",
      "bom-ref": "BomRef.055281773534456735.8737068040330332",
      "version": "unknown"
    },
    {
      "name": "pkg:rpm/centos/libattr@2.4.46-13.el7?arch=x86_64&distro=centos-7.9.2009",
      "type": "library",
      "bom-ref": "BomRef.8667189490557057.3290089063513786",
      "version": "unknown"
    },
    {
      "name": "pkg:rpm/centos/libblkid@2.23.2-65.el7?arch=x86_64&distro=centos-7.9.2009",
      "type": "library",
      "bom-ref": "BomRef.5010019553721136.5657988123749819",
      "version": "unknown"
    },
    {
      "name": "pkg:rpm/centos/libcap-ng@0.7.5-4.el7?arch=x86_64&distro=centos-7.9.2009",
      "type": "library",
      "bom-ref": "BomRef.9551234838225656.9213149137759589",
      "version": "unknown"
    },
    {
      "name": "pkg:rpm/centos/libcap@2.22-11.el7?arch=x86_64&distro=centos-7.9.2009",
      "type": "library",
      "bom-ref": "BomRef.7939819540278187.5418607342190763",
      "version": "unknown"
    },
    {
      "name": "pkg:rpm/centos/libcom_err@1.42.9-19.el7?arch=x86_64&distro=centos-7.9.2009",
      "type": "library",
      "bom-ref": "BomRef.47373043936031745.5694667143184716",
      "version": "unknown"
    },
    {
      "name": "pkg:rpm/centos/libcurl@7.29.0-59.el7?arch=x86_64&distro=centos-7.9.2009",
      "type": "library",
      "bom-ref": "BomRef.2705250193258294.18583844855572262",
      "version": "unknown"
    },
    {
      "name": "pkg:rpm/centos/libdb-utils@5.3.21-25.el7?arch=x86_64&distro=centos-7.9.2009",
      "type": "library",
      "bom-ref": "BomRef.7643075368628234.394384352153599",
      "version": "unknown"
    },
    {
      "name": "pkg:rpm/centos/libdb@5.3.21-25.el7?arch=x86_64&distro=centos-7.9.2009",
      "type": "library",
      "bom-ref": "BomRef.4790588771748582.6411225422428273",
      "version": "unknown"
    },
    {
      "name": "pkg:rpm/centos/libffi@3.0.13-19.el7?arch=x86_64&distro=centos-7.9.2009",
      "type": "library",
      "bom-ref": "BomRef.8697643274403607.9244141858229975",
      "version": "unknown"
    },
    {
      "name": "pkg:rpm/centos/libgcc@4.8.5-44.el7?arch=x86_64&distro=centos-7.9.2009",
      "type": "library",
      "bom-ref": "BomRef.6684533381970013.1591904398140409",
      "version": "unknown"
    },
    {
      "name": "pkg:rpm/centos/libgcrypt@1.5.3-14.el7?arch=x86_64&distro=centos-7.9.2009",
      "type": "library",
      "bom-ref": "BomRef.46538868473956774.8189112356011137",
      "version": "unknown"
    },
    {
      "name": "pkg:rpm/centos/libgpg-error@1.12-3.el7?arch=x86_64&distro=centos-7.9.2009",
      "type": "library",
      "bom-ref": "BomRef.8887838325397045.9350095567880532",
      "version": "unknown"
    },
    {
      "name": "pkg:rpm/centos/libidn@1.28-4.el7?arch=x86_64&distro=centos-7.9.2009",
      "type": "library",
      "bom-ref": "BomRef.886341185060498.7209855120228137",
      "version": "unknown"
    },
    {
      "name": "pkg:rpm/centos/libmount@2.23.2-65.el7?arch=x86_64&distro=centos-7.9.2009",
      "type": "library",
      "bom-ref": "BomRef.7444794338435629.2577597325025265",
      "version": "unknown"
    },
    {
      "name": "pkg:rpm/centos/libpwquality@1.2.3-5.el7?arch=x86_64&distro=centos-7.9.2009",
      "type": "library",
      "bom-ref": "BomRef.7409536391314157.6831896820525055",
      "version": "unknown"
    },
    {
      "name": "pkg:rpm/centos/libselinux@2.5-15.el7?arch=x86_64&distro=centos-7.9.2009",
      "type": "library",
      "bom-ref": "BomRef.4959378946090258.8173692139455248",
      "version": "unknown"
    },
    {
      "name": "pkg:rpm/centos/libsemanage@2.5-14.el7?arch=x86_64&distro=centos-7.9.2009",
      "type": "library",
      "bom-ref": "BomRef.30890741493735263.44419363445007753",
      "version": "unknown"
    },
    {
      "name": "pkg:rpm/centos/libsepol@2.5-10.el7?arch=x86_64&distro=centos-7.9.2009",
      "type": "library",
      "bom-ref": "BomRef.3934545941634071.08345323379101399",
      "version": "unknown"
    },
    {
      "name": "pkg:rpm/centos/libsmartcols@2.23.2-65.el7?arch=x86_64&distro=centos-7.9.2009",
      "type": "library",
      "bom-ref": "BomRef.7029642512180814.5555895094100395",
      "version": "unknown"
    },
    {
      "name": "pkg:rpm/centos/libssh2@1.8.0-4.el7?arch=x86_64&distro=centos-7.9.2009",
      "type": "library",
      "bom-ref": "BomRef.8913192243643914.2562558584536698",
      "version": "unknown"
    },
    {
      "name": "pkg:rpm/centos/libstdc%2B%2B@4.8.5-44.el7?arch=x86_64&distro=centos-7.9.2009",
      "type": "library",
      "bom-ref": "BomRef.8427782588882277.3444399947044008",
      "version": "unknown"
    },
    {
      "name": "pkg:rpm/centos/libtasn1@4.10-1.el7?arch=x86_64&distro=centos-7.9.2009",
      "type": "library",
      "bom-ref": "BomRef.6049781965275146.9126958622673069",
      "version": "unknown"
    },
    {
      "name": "pkg:rpm/centos/libuser@0.60-9.el7?arch=x86_64&distro=centos-7.9.2009",
      "type": "library",
      "bom-ref": "BomRef.4048789714699442.3605213520615854",
      "version": "unknown"
    },
    {
      "name": "pkg:rpm/centos/libutempter@1.1.6-4.el7?arch=x86_64&distro=centos-7.9.2009",
      "type": "library",
      "bom-ref": "BomRef.1813946462367355.851964614086686",
      "version": "unknown"
    },
    {
      "name": "pkg:rpm/centos/libuuid@2.23.2-65.el7?arch=x86_64&distro=centos-7.9.2009",
      "type": "library",
      "bom-ref": "BomRef.8856308642162309.861413307131058",
      "version": "unknown"
    },
    {
      "name": "pkg:rpm/centos/libverto@0.2.5-4.el7?arch=x86_64&distro=centos-7.9.2009",
      "type": "library",
      "bom-ref": "BomRef.4886027279476527.8228142696125779",
      "version": "unknown"
    },
    {
      "name": "pkg:rpm/centos/libxml2-python@2.9.1-6.el7.5?arch=x86_64&distro=centos-7.9.2009",
      "type": "library",
      "bom-ref": "BomRef.4555454864853925.41555854696678507",
      "version": "unknown"
    },
    {
      "name": "pkg:rpm/centos/libxml2@2.9.1-6.el7.5?arch=x86_64&distro=centos-7.9.2009",
      "type": "library",
      "bom-ref": "BomRef.9012058949879385.8642435859541833",
      "version": "unknown"
    },
    {
      "name": "pkg:rpm/centos/lua@5.1.4-15.el7?arch=x86_64&distro=centos-7.9.2009",
      "type": "library",
      "bom-ref": "BomRef.9543921988087452.7225843850150544",
      "version": "unknown"
    },
    {
      "name": "pkg:rpm/centos/lz4@1.8.3-1.el7?arch=x86_64&distro=centos-7.9.2009",
      "type": "library",
      "bom-ref": "BomRef.3498315774854065.16096734142206037",
      "version": "unknown"
    },
    {
      "name": "pkg:rpm/centos/ncurses-base@5.9-14.20130511.el7_4?arch=noarch&distro=centos-7.9.2009",
      "type": "library",
      "bom-ref": "BomRef.8334891432288822.45795039089387823",
      "version": "unknown"
    },
    {
      "name": "pkg:rpm/centos/ncurses-libs@5.9-14.20130511.el7_4?arch=x86_64&distro=centos-7.9.2009",
      "type": "library",
      "bom-ref": "BomRef.6238528413172444.19213442922506874",
      "version": "unknown"
    },
    {
      "name": "pkg:rpm/centos/ncurses@5.9-14.20130511.el7_4?arch=x86_64&distro=centos-7.9.2009",
      "type": "library",
      "bom-ref": "BomRef.3195706808242019.7364347884236024",
      "version": "unknown"
    },
    {
      "name": "pkg:rpm/centos/nspr@4.25.0-2.el7_9?arch=x86_64&distro=centos-7.9.2009",
      "type": "library",
      "bom-ref": "BomRef.6862769621447209.967507930635375",
      "version": "unknown"
    },
    {
      "name": "pkg:rpm/centos/nss-pem@1.0.3-7.el7?arch=x86_64&distro=centos-7.9.2009",
      "type": "library",
      "bom-ref": "BomRef.814593152925056.31240117238564813",
      "version": "unknown"
    },
    {
      "name": "pkg:rpm/centos/nss-softokn-freebl@3.53.1-6.el7_9?arch=x86_64&distro=centos-7.9.2009",
      "type": "library",
      "bom-ref": "BomRef.5542748180157804.3930952649308992",
      "version": "unknown"
    },
    {
      "name": "pkg:rpm/centos/nss-softokn@3.53.1-6.el7_9?arch=x86_64&distro=centos-7.9.2009",
      "type": "library",
      "bom-ref": "BomRef.47723996773660604.6749478586608814",
      "version": "unknown"
    },
    {
      "name": "pkg:rpm/centos/nss-sysinit@3.53.1-3.el7_9?arch=x86_64&distro=centos-7.9.2009",
      "type": "library",
      "bom-ref": "BomRef.8006393402239098.4666929798988605",
      "version": "unknown"
    },
    {
      "name": "pkg:rpm/centos/nss-tools@3.53.1-3.el7_9?arch=x86_64&distro=centos-7.9.2009",
      "type": "library",
      "bom-ref": "BomRef.7000002960800513.8576172039618027",
      "version": "unknown"
    },
    {
      "name": "pkg:rpm/centos/nss-util@3.53.1-1.el7_9?arch=x86_64&distro=centos-7.9.2009",
      "type": "library",
      "bom-ref": "BomRef.5798775058855651.7591171885782486",
      "version": "unknown"
    },
    {
      "name": "pkg:rpm/centos/nss@3.53.1-3.el7_9?arch=x86_64&distro=centos-7.9.2009",
      "type": "library",
      "bom-ref": "BomRef.9474213003526996.752763757863455",
      "version": "unknown"
    },
    {
      "name": "pkg:rpm/centos/openldap@2.4.44-22.el7?arch=x86_64&distro=centos-7.9.2009",
      "type": "library",
      "bom-ref": "BomRef.7895181935851667.018996242220371995",
      "version": "unknown"
    },
    {
      "name": "pkg:rpm/centos/openssl-libs@1.0.2k-19.el7?arch=x86_64&distro=centos-7.9.2009&epoch=1",
      "type": "library",
      "bom-ref": "BomRef.8128886103442383.8369284112703149",
      "version": "unknown"
    },
    {
      "name": "pkg:rpm/centos/p11-kit-trust@0.23.5-3.el7?arch=x86_64&distro=centos-7.9.2009",
      "type": "library",
      "bom-ref": "BomRef.9449621915662985.18331485194585295",
      "version": "unknown"
    },
    {
      "name": "pkg:rpm/centos/p11-kit@0.23.5-3.el7?arch=x86_64&distro=centos-7.9.2009",
      "type": "library",
      "bom-ref": "BomRef.36209744185831294.8138358372671167",
      "version": "unknown"
    },
    {
      "name": "pkg:rpm/centos/pam@1.1.8-23.el7?arch=x86_64&distro=centos-7.9.2009",
      "type": "library",
      "bom-ref": "BomRef.34765062897750365.22107471345725438",
      "version": "unknown"
    },
    {
      "name": "pkg:rpm/centos/passwd@0.79-6.el7?arch=x86_64&distro=centos-7.9.2009",
      "type": "library",
      "bom-ref": "BomRef.672049737170431.22326891358917367",
      "version": "unknown"
    },
    {
      "name": "pkg:rpm/centos/pcre@8.32-17.el7?arch=x86_64&distro=centos-7.9.2009",
      "type": "library",
      "bom-ref": "BomRef.46502013186201085.9108923599354485",
      "version": "unknown"
    },
    {
      "name": "pkg:rpm/centos/pinentry@0.8.1-17.el7?arch=x86_64&distro=centos-7.9.2009",
      "type": "library",
      "bom-ref": "BomRef.06442741136731589.42460298589500156",
      "version": "unknown"
    },
    {
      "name": "pkg:rpm/centos/pkgconfig@0.27.1-4.el7?arch=x86_64&distro=centos-7.9.2009&epoch=1",
      "type": "library",
      "bom-ref": "BomRef.3392239156162711.20189195507214852",
      "version": "unknown"
    },
    {
      "name": "pkg:rpm/centos/popt@1.13-16.el7?arch=x86_64&distro=centos-7.9.2009",
      "type": "library",
      "bom-ref": "BomRef.8319671758737434.3874282118419835",
      "version": "unknown"
    },
    {
      "name": "pkg:rpm/centos/procps-ng@3.3.10-28.el7?arch=x86_64&distro=centos-7.9.2009",
      "type": "library",
      "bom-ref": "BomRef.86510174762046.0036254408100384605",
      "version": "unknown"
    },
    {
      "name": "pkg:rpm/centos/pth@2.0.7-23.el7?arch=x86_64&distro=centos-7.9.2009",
      "type": "library",
      "bom-ref": "BomRef.6229149125761952.5741970172408265",
      "version": "unknown"
    },
    {
      "name": "pkg:rpm/centos/pygpgme@0.3-9.el7?arch=x86_64&distro=centos-7.9.2009",
      "type": "library",
      "bom-ref": "BomRef.8917237585569491.45259873943245654",
      "version": "unknown"
    },
    {
      "name": "pkg:rpm/centos/pyliblzma@0.5.3-11.el7?arch=x86_64&distro=centos-7.9.2009",
      "type": "library",
      "bom-ref": "BomRef.12634523382888185.16951539618005262",
      "version": "unknown"
    },
    {
      "name": "pkg:rpm/centos/python-chardet@2.2.1-3.el7?arch=noarch&distro=centos-7.9.2009",
      "type": "library",
      "bom-ref": "BomRef.4533028365084485.9710242854146007",
      "version": "unknown"
    },
    {
      "name": "pkg:rpm/centos/python-gobject-base@3.22.0-1.el7_4.1?arch=x86_64&distro=centos-7.9.2009",
      "type": "library",
      "bom-ref": "BomRef.00220718568002376.9400253389255641",
      "version": "unknown"
    },
    {
      "name": "pkg:rpm/centos/python-iniparse@0.4-9.el7?arch=noarch&distro=centos-7.9.2009",
      "type": "library",
      "bom-ref": "BomRef.5066196666855471.3307682667796954",
      "version": "unknown"
    },
    {
      "name": "pkg:rpm/centos/python-kitchen@1.1.1-5.el7?arch=noarch&distro=centos-7.9.2009",
      "type": "library",
      "bom-ref": "BomRef.013275730938444474.49747937250809626",
      "version": "unknown"
    },
    {
      "name": "pkg:rpm/centos/python-libs@2.7.5-89.el7?arch=x86_64&distro=centos-7.9.2009",
      "type": "library",
      "bom-ref": "BomRef.017430620072204417.844902489330875",
      "version": "unknown"
    },
    {
      "name": "pkg:rpm/centos/python-pycurl@7.19.0-19.el7?arch=x86_64&distro=centos-7.9.2009",
      "type": "library",
      "bom-ref": "BomRef.27164766798168016.2703144002373641",
      "version": "unknown"
    },
    {
      "name": "pkg:rpm/centos/python-urlgrabber@3.10-10.el7?arch=noarch&distro=centos-7.9.2009",
      "type": "library",
      "bom-ref": "BomRef.33684947783861263.012520512779695347",
      "version": "unknown"
    },
    {
      "name": "pkg:rpm/centos/python@2.7.5-89.el7?arch=x86_64&distro=centos-7.9.2009",
      "type": "library",
      "bom-ref": "BomRef.5533104227868851.8033999424504054",
      "version": "unknown"
    },
    {
      "name": "pkg:rpm/centos/pyxattr@0.5.1-5.el7?arch=x86_64&distro=centos-7.9.2009",
      "type": "library",
      "bom-ref": "BomRef.9335194056541933.6581218695457874",
      "version": "unknown"
    },
    {
      "name": "pkg:rpm/centos/qrencode-libs@3.4.1-3.el7?arch=x86_64&distro=centos-7.9.2009",
      "type": "library",
      "bom-ref": "BomRef.3026323107558184.06681851290715468",
      "version": "unknown"
    },
    {
      "name": "pkg:rpm/centos/readline@6.2-11.el7?arch=x86_64&distro=centos-7.9.2009",
      "type": "library",
      "bom-ref": "BomRef.9458203765062017.9059459931882156",
      "version": "unknown"
    },
    {
      "name": "pkg:rpm/centos/rootfiles@8.1-11.el7?arch=noarch&distro=centos-7.9.2009",
      "type": "library",
      "bom-ref": "BomRef.15810767743355147.6053859461320094",
      "version": "unknown"
    },
    {
      "name": "pkg:rpm/centos/rpm-build-libs@4.11.3-45.el7?arch=x86_64&distro=centos-7.9.2009",
      "type": "library",
      "bom-ref": "BomRef.9105788447659425.5903817558848735",
      "version": "unknown"
    },
    {
      "name": "pkg:rpm/centos/rpm-libs@4.11.3-45.el7?arch=x86_64&distro=centos-7.9.2009",
      "type": "library",
      "bom-ref": "BomRef.15076870899981953.6633781319342072",
      "version": "unknown"
    },
    {
      "name": "pkg:rpm/centos/rpm-python@4.11.3-45.el7?arch=x86_64&distro=centos-7.9.2009",
      "type": "library",
      "bom-ref": "BomRef.08841347830938262.9618312134939507",
      "version": "unknown"
    },
    {
      "name": "pkg:rpm/centos/rpm@4.11.3-45.el7?arch=x86_64&distro=centos-7.9.2009",
      "type": "library",
      "bom-ref": "BomRef.24874492921958002.6899724220523172",
      "version": "unknown"
    },
    {
      "name": "pkg:rpm/centos/sed@4.2.2-7.el7?arch=x86_64&distro=centos-7.9.2009",
      "type": "library",
      "bom-ref": "BomRef.5674407609381681.022180079755491744",
      "version": "unknown"
    },
    {
      "name": "pkg:rpm/centos/setup@2.8.71-11.el7?arch=noarch&distro=centos-7.9.2009",
      "type": "library",
      "bom-ref": "BomRef.22038733579669623.4783478835232551",
      "version": "unknown"
    },
    {
      "name": "pkg:rpm/centos/shadow-utils@4.6-5.el7?arch=x86_64&distro=centos-7.9.2009&epoch=2",
      "type": "library",
      "bom-ref": "BomRef.10942467001581924.08997947923827398",
      "version": "unknown"
    },
    {
      "name": "pkg:rpm/centos/shared-mime-info@1.8-5.el7?arch=x86_64&distro=centos-7.9.2009",
      "type": "library",
      "bom-ref": "BomRef.7102766486771992.49653558115444096",
      "version": "unknown"
    },
    {
      "name": "pkg:rpm/centos/sqlite@3.7.17-8.el7_7.1?arch=x86_64&distro=centos-7.9.2009",
      "type": "library",
      "bom-ref": "BomRef.9312443860029734.5181854661024881",
      "version": "unknown"
    },
    {
      "name": "pkg:rpm/centos/systemd-libs@219-78.el7?arch=x86_64&distro=centos-7.9.2009",
      "type": "library",
      "bom-ref": "BomRef.08668541373588312.1725346438705757",
      "version": "unknown"
    },
    {
      "name": "pkg:rpm/centos/systemd@219-78.el7?arch=x86_64&distro=centos-7.9.2009",
      "type": "library",
      "bom-ref": "BomRef.3566743278951017.7022088814409161",
      "version": "unknown"
    },
    {
      "name": "pkg:rpm/centos/tar@1.26-35.el7?arch=x86_64&distro=centos-7.9.2009&epoch=2",
      "type": "library",
      "bom-ref": "BomRef.07838849536073544.31005096468217097",
      "version": "unknown"
    },
    {
      "name": "pkg:rpm/centos/tzdata@2020d-2.el7?arch=noarch&distro=centos-7.9.2009",
      "type": "library",
      "bom-ref": "BomRef.8959186262053416.8964785106518575",
      "version": "unknown"
    },
    {
      "name": "pkg:rpm/centos/ustr@1.0.4-16.el7?arch=x86_64&distro=centos-7.9.2009",
      "type": "library",
      "bom-ref": "BomRef.8557107532354669.7833104129870408",
      "version": "unknown"
    },
    {
      "name": "pkg:rpm/centos/util-linux@2.23.2-65.el7?arch=x86_64&distro=centos-7.9.2009",
      "type": "library",
      "bom-ref": "BomRef.6063912485771416.312914175475967",
      "version": "unknown"
    },
    {
      "name": "pkg:rpm/centos/vim-minimal@7.4.629-7.el7?arch=x86_64&distro=centos-7.9.2009&epoch=2",
      "type": "library",
      "bom-ref": "BomRef.14671596241459317.7706657957152158",
      "version": "unknown"
    },
    {
      "name": "pkg:rpm/centos/xz-libs@5.2.2-1.el7?arch=x86_64&distro=centos-7.9.2009",
      "type": "library",
      "bom-ref": "BomRef.20525385563201737.0536643096858791",
      "version": "unknown"
    },
    {
      "name": "pkg:rpm/centos/xz@5.2.2-1.el7?arch=x86_64&distro=centos-7.9.2009",
      "type": "library",
      "bom-ref": "BomRef.8800027629466532.5679214817870296",
      "version": "unknown"
    },
    {
      "name": "pkg:rpm/centos/yum-metadata-parser@1.1.4-10.el7?arch=x86_64&distro=centos-7.9.2009",
      "type": "library",
      "bom-ref": "BomRef.15204947482051578.680892082236111",
      "version": "unknown"
    },
    {
      "name": "pkg:rpm/centos/yum-plugin-fastestmirror@1.1.31-54.el7_8?arch=noarch&distro=centos-7.9.2009",
      "type": "library",
      "bom-ref": "BomRef.4840460880463867.7868002074381268",
      "version": "unknown"
    },
    {
      "name": "pkg:rpm/centos/yum-plugin-ovl@1.1.31-54.el7_8?arch=noarch&distro=centos-7.9.2009",
      "type": "library",
      "bom-ref": "BomRef.046201384183194416.7153972558318439",
      "version": "unknown"
    },
    {
      "name": "pkg:rpm/centos/yum-utils@1.1.31-54.el7_8?arch=noarch&distro=centos-7.9.2009",
      "type": "library",
      "bom-ref": "BomRef.06471282000115353.6304173931237735",
      "version": "unknown"
    },
    {
      "name": "pkg:rpm/centos/yum@3.4.3-168.el7.centos?arch=noarch&distro=centos-7.9.2009",
      "type": "library",
      "bom-ref": "BomRef.4806774059496499.355505218075278",
      "version": "unknown"
    },
    {
      "name": "pkg:rpm/centos/zlib@1.2.7-18.el7?arch=x86_64&distro=centos-7.9.2009",
      "type": "library",
      "bom-ref": "BomRef.4189278993854423.6280345562612181",
      "version": "unknown"
    },
    {
      "name": "pkgconfig",
      "type": "library",
      "bom-ref": "BomRef.11250165345723151.13485070872451732",
      "version": "1:0.27.1-4.el7"
    },
    {
      "name": "popt",
      "type": "library",
      "bom-ref": "BomRef.5775894136360654.035001192284008886",
      "version": "1.13-16.el7"
    },
    {
      "name": "procps-ng",
      "type": "library",
      "bom-ref": "BomRef.8515599379047767.9726387072919376",
      "version": "3.3.10-28.el7"
    },
    {
      "name": "pth",
      "type": "library",
      "bom-ref": "BomRef.8698514761143893.8621563258245687",
      "version": "2.0.7-23.el7"
    },
    {
      "name": "pygpgme",
      "type": "library",
      "bom-ref": "BomRef.4965980667130342.39786641976415993",
      "version": "0.3-9.el7"
    },
    {
      "name": "pyliblzma",
      "type": "library",
      "bom-ref": "BomRef.02706650076238104.07618723052387566",
      "version": "0.5.3-11.el7"
    },
    {
      "name": "python",
      "type": "library",
      "bom-ref": "BomRef.7078952103248536.4496411390556796",
      "version": "2.7.5-89.el7"
    },
    {
      "name": "python-chardet",
      "type": "library",
      "bom-ref": "BomRef.32212116970437266.2048772958802848",
      "version": "2.2.1-3.el7"
    },
    {
      "name": "python-gobject-base",
      "type": "library",
      "bom-ref": "BomRef.47376881244372615.3717763174675781",
      "version": "3.22.0-1.el7_4.1"
    },
    {
      "name": "python-iniparse",
      "type": "library",
      "bom-ref": "BomRef.2923854921258543.044934131235749075",
      "version": "0.4-9.el7"
    },
    {
      "name": "python-kitchen",
      "type": "library",
      "bom-ref": "BomRef.7070597787255379.510726977241715",
      "version": "1.1.1-5.el7"
    },
    {
      "name": "python-libs",
      "type": "library",
      "bom-ref": "BomRef.4474208402550103.03802882293588217",
      "version": "2.7.5-89.el7"
    },
    {
      "name": "python-pycurl",
      "type": "library",
      "bom-ref": "BomRef.4029864809446252.09458249273216346",
      "version": "7.19.0-19.el7"
    },
    {
      "name": "python-urlgrabber",
      "type": "library",
      "bom-ref": "BomRef.01605595800528392.6997718836969521",
      "version": "3.10-10.el7"
    },
    {
      "name": "pyxattr",
      "type": "library",
      "bom-ref": "BomRef.6714605925232229.7543284928796826",
      "version": "0.5.1-5.el7"
    },
    {
      "name": "qrencode-libs",
      "type": "library",
      "bom-ref": "BomRef.9630967861977339.09678278006981433",
      "version": "3.4.1-3.el7"
    },
    {
      "name": "readline",
      "type": "library",
      "bom-ref": "BomRef.5052613655781848.7341701481672441",
      "version": "6.2-11.el7"
    },
    {
      "name": "rootfiles",
      "type": "library",
      "bom-ref": "BomRef.9707614144704962.9115148897213815",
      "version": "8.1-11.el7"
    },
    {
      "name": "rpm",
      "type": "library",
      "bom-ref": "BomRef.17911703593542094.4655116816093825",
      "version": "4.11.3-45.el7"
    },
    {
      "name": "rpm-build-libs",
      "type": "library",
      "bom-ref": "BomRef.8863867725004482.8531947056724442",
      "version": "4.11.3-45.el7"
    },
    {
      "name": "rpm-libs",
      "type": "library",
      "bom-ref": "BomRef.5767953029467596.010556248392962653",
      "version": "4.11.3-45.el7"
    },
    {
      "name": "rpm-python",
      "type": "library",
      "bom-ref": "BomRef.832428181245846.9797654147548439",
      "version": "4.11.3-45.el7"
    },
    {
      "name": "sed",
      "type": "library",
      "bom-ref": "BomRef.5018513199607161.3337204841226755",
      "version": "4.2.2-7.el7"
    },
    {
      "name": "setup",
      "type": "library",
      "bom-ref": "BomRef.3448349710249058.4123611222269188",
      "version": "2.8.71-11.el7"
    },
    {
      "name": "shadow-utils",
      "type": "library",
      "bom-ref": "BomRef.945734397771488.7891064872735736",
      "version": "2:4.6-5.el7"
    },
    {
      "name": "shared-mime-info",
      "type": "library",
      "bom-ref": "BomRef.4829884291936871.7123644307401936",
      "version": "1.8-5.el7"
    },
    {
      "name": "sqlite",
      "type": "library",
      "bom-ref": "BomRef.504704650313748.12256129801796811",
      "version": "3.7.17-8.el7_7.1"
    },
    {
      "name": "systemd",
      "type": "library",
      "bom-ref": "BomRef.4884427677844084.6103957282605341",
      "version": "219-78.el7"
    },
    {
      "name": "systemd-libs",
      "type": "library",
      "bom-ref": "BomRef.9283132601079156.03505387149439532",
      "version": "219-78.el7"
    },
    {
      "name": "tar",
      "type": "library",
      "bom-ref": "BomRef.5622834153885823.48318763443828383",
      "version": "2:1.26-35.el7"
    },
    {
      "name": "tzdata",
      "type": "library",
      "bom-ref": "BomRef.32351517968295407.9140654815918946",
      "version": "2020d-2.el7"
    },
    {
      "name": "ustr",
      "type": "library",
      "bom-ref": "BomRef.647282982919074.00907478953549945",
      "version": "1.0.4-16.el7"
    },
    {
      "name": "util-linux",
      "type": "library",
      "bom-ref": "BomRef.5276356143626476.4172493114038509",
      "version": "2.23.2-65.el7"
    },
    {
      "name": "vim-minimal",
      "type": "library",
      "bom-ref": "BomRef.37427670808859614.02560288929351251",
      "version": "2:7.4.629-7.el7"
    },
    {
      "name": "xz",
      "type": "library",
      "bom-ref": "BomRef.3477760215057234.8986338458249457",
      "version": "5.2.2-1.el7"
    },
    {
      "name": "xz-libs",
      "type": "library",
      "bom-ref": "BomRef.4671208111214331.8880812726504487",
      "version": "5.2.2-1.el7"
    },
    {
      "name": "yum",
      "type": "library",
      "bom-ref": "BomRef.48603254202922586.9644438314022694",
      "version": "3.4.3-168.el7.centos"
    },
    {
      "name": "yum-metadata-parser",
      "type": "library",
      "bom-ref": "BomRef.1229956186282668.5103842095418231",
      "version": "1.1.4-10.el7"
    },
    {
      "name": "yum-plugin-fastestmirror",
      "type": "library",
      "bom-ref": "BomRef.4414008163725943.6238573278148198",
      "version": "1.1.31-54.el7_8"
    },
    {
      "name": "yum-plugin-ovl",
      "type": "library",
      "bom-ref": "BomRef.8223702396343866.46828330007693497",
      "version": "1.1.31-54.el7_8"
    },
    {
      "name": "yum-utils",
      "type": "library",
      "bom-ref": "BomRef.1659020288322307.2157473419232776",
      "version": "1.1.31-54.el7_8"
    },
    {
      "name": "zlib",
      "type": "library",
      "bom-ref": "BomRef.799883482545087.7631765886229174",
      "version": "1.2.7-18.el7"
    }
  ],
  "specVersion": "1.6",
  "dependencies": [
    {
      "ref": "BomRef.057993642585890015.8648595561273664"
    },
    {
      "ref": "BomRef.3324682176988484.6116024106049724"
    },
    {
      "ref": "BomRef.8482080066185224.10958285108431443"
    },
    {
      "ref": "BomRef.09646571441629337.15215251842763444"
    },
    {
      "ref": "BomRef.04053329806906536.42725921623339147"
    },
    {
      "ref": "BomRef.7134131471678684.7889429814817616"
    },
    {
      "ref": "BomRef.33857822218813316.7552305384093357"
    },
    {
      "ref": "BomRef.6031860677211648.3239693754658175"
    },
    {
      "ref": "BomRef.02183064099084342.566083058802005"
    },
    {
      "ref": "BomRef.45487917549634593.4177623362994095"
    },
    {
      "ref": "BomRef.6715443298626859.6217813837827428"
    },
    {
      "ref": "BomRef.46902099014219756.6491639247271938"
    },
    {
      "ref": "BomRef.38197213244674333.38584593667802947"
    },
    {
      "ref": "BomRef.7111467413978058.506607624759521"
    },
    {
      "ref": "BomRef.6112987920128037.21125736682874563"
    },
    {
      "ref": "BomRef.3784304008894782.5118519880466966"
    },
    {
      "ref": "BomRef.4888581320832842.3539499570520953"
    },
    {
      "ref": "BomRef.8296968833052679.34668572699676536"
    },
    {
      "ref": "BomRef.10978319758943689.9304933730628435"
    },
    {
      "ref": "BomRef.08414766719086875.8459684995663234"
    },
    {
      "ref": "BomRef.7603726149683712.44842367717705334"
    },
    {
      "ref": "BomRef.6241981551378307.24462842266975637"
    },
    {
      "ref": "BomRef.805817690117059.980527669909242"
    },
    {
      "ref": "BomRef.2177583145952482.2085145602198637"
    },
    {
      "ref": "BomRef.757285176615639.30079946128356727"
    },
    {
      "ref": "BomRef.0500009078605308.16525287386835474"
    },
    {
      "ref": "BomRef.7410904425378922.8150480979104315"
    },
    {
      "ref": "BomRef.7250010128803137.2666620096170671"
    },
    {
      "ref": "BomRef.1280962955337872.6380582352989193"
    },
    {
      "ref": "BomRef.3585567576707819.9319653832146283"
    },
    {
      "ref": "BomRef.6218149150985431.3039539087537433"
    },
    {
      "ref": "BomRef.2370556436538903.22947977889555993"
    },
    {
      "ref": "BomRef.6332229786811459.8819197214733189"
    },
    {
      "ref": "BomRef.6249323781848204.2800542636206207"
    },
    {
      "ref": "BomRef.1535708737125726.9851514921168668"
    },
    {
      "ref": "BomRef.4578503510904596.6764302156482087"
    },
    {
      "ref": "BomRef.8789965874274014.0549419345103106"
    },
    {
      "ref": "BomRef.6266479496990721.6755247596276939"
    },
    {
      "ref": "BomRef.663987839268528.04752075229213937"
    },
    {
      "ref": "BomRef.8406906183661705.17813406204012705"
    },
    {
      "ref": "BomRef.6410873741070992.036857118978913195"
    },
    {
      "ref": "BomRef.44172163091307226.4004541134644547"
    },
    {
      "ref": "BomRef.989883659417556.9319636192227638"
    },
    {
      "ref": "BomRef.30571853313711084.4460882537765475"
    },
    {
      "ref": "BomRef.10248628051791409.5040119349763146"
    },
    {
      "ref": "BomRef.6194425528485259.33842079640205003"
    },
    {
      "ref": "BomRef.8126181861988361.41434738507603197"
    },
    {
      "ref": "BomRef.7869926598497546.018128985081250604"
    },
    {
      "ref": "BomRef.3821354631203039.10719869032732732"
    },
    {
      "ref": "BomRef.24519108893793717.11547544648482422"
    },
    {
      "ref": "BomRef.6547913237021074.33136721587494666"
    },
    {
      "ref": "BomRef.6072262996782428.5145314283773903"
    },
    {
      "ref": "BomRef.07738674078897034.5919048846959302"
    },
    {
      "ref": "BomRef.9054974962289634.501556331610808"
    },
    {
      "ref": "BomRef.05398672634921997.7650355545711406"
    },
    {
      "ref": "BomRef.6610941716539932.2687495826670516"
    },
    {
      "ref": "BomRef.26407949568515654.6908314029997384"
    },
    {
      "ref": "BomRef.9170892163702018.5490025919519991"
    },
    {
      "ref": "BomRef.055281773534456735.8737068040330332"
    },
    {
      "ref": "BomRef.8667189490557057.3290089063513786"
    },
    {
      "ref": "BomRef.5010019553721136.5657988123749819"
    },
    {
      "ref": "BomRef.9551234838225656.9213149137759589"
    },
    {
      "ref": "BomRef.7939819540278187.5418607342190763"
    },
    {
      "ref": "BomRef.47373043936031745.5694667143184716"
    },
    {
      "ref": "BomRef.2705250193258294.18583844855572262"
    },
    {
      "ref": "BomRef.7643075368628234.394384352153599"
    },
    {
      "ref": "BomRef.4790588771748582.6411225422428273"
    },
    {
      "ref": "BomRef.8697643274403607.9244141858229975"
    },
    {
      "ref": "BomRef.6684533381970013.1591904398140409"
    },
    {
      "ref": "BomRef.46538868473956774.8189112356011137"
    },
    {
      "ref": "BomRef.8887838325397045.9350095567880532"
    },
    {
      "ref": "BomRef.886341185060498.7209855120228137"
    },
    {
      "ref": "BomRef.7444794338435629.2577597325025265"
    },
    {
      "ref": "BomRef.7409536391314157.6831896820525055"
    },
    {
      "ref": "BomRef.4959378946090258.8173692139455248"
    },
    {
      "ref": "BomRef.30890741493735263.44419363445007753"
    },
    {
      "ref": "BomRef.3934545941634071.08345323379101399"
    },
    {
      "ref": "BomRef.7029642512180814.5555895094100395"
    },
    {
      "ref": "BomRef.8913192243643914.2562558584536698"
    },
    {
      "ref": "BomRef.8427782588882277.3444399947044008"
    },
    {
      "ref": "BomRef.6049781965275146.9126958622673069"
    },
    {
      "ref": "BomRef.4048789714699442.3605213520615854"
    },
    {
      "ref": "BomRef.1813946462367355.851964614086686"
    },
    {
      "ref": "BomRef.8856308642162309.861413307131058"
    },
    {
      "ref": "BomRef.4886027279476527.8228142696125779"
    },
    {
      "ref": "BomRef.4555454864853925.41555854696678507"
    },
    {
      "ref": "BomRef.9012058949879385.8642435859541833"
    },
    {
      "ref": "BomRef.9543921988087452.7225843850150544"
    },
    {
      "ref": "BomRef.3498315774854065.16096734142206037"
    },
    {
      "ref": "BomRef.8334891432288822.45795039089387823"
    },
    {
      "ref": "BomRef.6238528413172444.19213442922506874"
    },
    {
      "ref": "BomRef.3195706808242019.7364347884236024"
    },
    {
      "ref": "BomRef.6862769621447209.967507930635375"
    },
    {
      "ref": "BomRef.814593152925056.31240117238564813"
    },
    {
      "ref": "BomRef.5542748180157804.3930952649308992"
    },
    {
      "ref": "BomRef.47723996773660604.6749478586608814"
    },
    {
      "ref": "BomRef.8006393402239098.4666929798988605"
    },
    {
      "ref": "BomRef.7000002960800513.8576172039618027"
    },
    {
      "ref": "BomRef.5798775058855651.7591171885782486"
    },
    {
      "ref": "BomRef.9474213003526996.752763757863455"
    },
    {
      "ref": "BomRef.7895181935851667.018996242220371995"
    },
    {
      "ref": "BomRef.8128886103442383.8369284112703149"
    },
    {
      "ref": "BomRef.9449621915662985.18331485194585295"
    },
    {
      "ref": "BomRef.36209744185831294.8138358372671167"
    },
    {
      "ref": "BomRef.34765062897750365.22107471345725438"
    },
    {
      "ref": "BomRef.672049737170431.22326891358917367"
    },
    {
      "ref": "BomRef.46502013186201085.9108923599354485"
    },
    {
      "ref": "BomRef.06442741136731589.42460298589500156"
    },
    {
      "ref": "BomRef.3392239156162711.20189195507214852"
    },
    {
      "ref": "BomRef.8319671758737434.3874282118419835"
    },
    {
      "ref": "BomRef.86510174762046.0036254408100384605"
    },
    {
      "ref": "BomRef.6229149125761952.5741970172408265"
    },
    {
      "ref": "BomRef.8917237585569491.45259873943245654"
    },
    {
      "ref": "BomRef.12634523382888185.16951539618005262"
    },
    {
      "ref": "BomRef.4533028365084485.9710242854146007"
    },
    {
      "ref": "BomRef.00220718568002376.9400253389255641"
    },
    {
      "ref": "BomRef.5066196666855471.3307682667796954"
    },
    {
      "ref": "BomRef.013275730938444474.49747937250809626"
    },
    {
      "ref": "BomRef.017430620072204417.844902489330875"
    },
    {
      "ref": "BomRef.27164766798168016.2703144002373641"
    },
    {
      "ref": "BomRef.33684947783861263.012520512779695347"
    },
    {
      "ref": "BomRef.5533104227868851.8033999424504054"
    },
    {
      "ref": "BomRef.9335194056541933.6581218695457874"
    },
    {
      "ref": "BomRef.3026323107558184.06681851290715468"
    },
    {
      "ref": "BomRef.9458203765062017.9059459931882156"
    },
    {
      "ref": "BomRef.15810767743355147.6053859461320094"
    },
    {
      "ref": "BomRef.9105788447659425.5903817558848735"
    },
    {
      "ref": "BomRef.15076870899981953.6633781319342072"
    },
    {
      "ref": "BomRef.08841347830938262.9618312134939507"
    },
    {
      "ref": "BomRef.24874492921958002.6899724220523172"
    },
    {
      "ref": "BomRef.5674407609381681.022180079755491744"
    },
    {
      "ref": "BomRef.22038733579669623.4783478835232551"
    },
    {
      "ref": "BomRef.10942467001581924.08997947923827398"
    },
    {
      "ref": "BomRef.7102766486771992.49653558115444096"
    },
    {
      "ref": "BomRef.9312443860029734.5181854661024881"
    },
    {
      "ref": "BomRef.08668541373588312.1725346438705757"
    },
    {
      "ref": "BomRef.3566743278951017.7022088814409161"
    },
    {
      "ref": "BomRef.07838849536073544.31005096468217097"
    },
    {
      "ref": "BomRef.8959186262053416.8964785106518575"
    },
    {
      "ref": "BomRef.8557107532354669.7833104129870408"
    },
    {
      "ref": "BomRef.6063912485771416.312914175475967"
    },
    {
      "ref": "BomRef.14671596241459317.7706657957152158"
    },
    {
      "ref": "BomRef.20525385563201737.0536643096858791"
    },
    {
      "ref": "BomRef.8800027629466532.5679214817870296"
    },
    {
      "ref": "BomRef.15204947482051578.680892082236111"
    },
    {
      "ref": "BomRef.4840460880463867.7868002074381268"
    },
    {
      "ref": "BomRef.046201384183194416.7153972558318439"
    },
    {
      "ref": "BomRef.06471282000115353.6304173931237735"
    },
    {
      "ref": "BomRef.4806774059496499.355505218075278"
    },
    {
      "ref": "BomRef.4189278993854423.6280345562612181"
    },
    {
      "ref": "BomRef.9683106869893632.3424927497040444"
    },
    {
      "ref": "BomRef.539435191342051.6789416876042998"
    },
    {
      "ref": "BomRef.07340813247072098.6402145831853399"
    },
    {
      "ref": "BomRef.12475269019461943.3212879832144697"
    },
    {
      "ref": "BomRef.7125279895436061.2760218177244482"
    },
    {
      "ref": "BomRef.6831752468118205.5447702736595869"
    },
    {
      "ref": "BomRef.5059320559169913.5696504869807414"
    },
    {
      "ref": "BomRef.5723073320108568.2403056152901244"
    },
    {
      "ref": "BomRef.3150762878689395.8752792954417918"
    },
    {
      "ref": "BomRef.13636069497244208.39483055158499936"
    },
    {
      "ref": "BomRef.5864308457377085.6237741792083524"
    },
    {
      "ref": "BomRef.5109353503070917.5248556956929712"
    },
    {
      "ref": "BomRef.5913696198156015.8449313250101518"
    },
    {
      "ref": "BomRef.9753508332280654.8546833527374805"
    },
    {
      "ref": "BomRef.07975902054800499.0715601581897517"
    },
    {
      "ref": "BomRef.09113560809499521.2962365642235617"
    },
    {
      "ref": "BomRef.41636622275731816.2927520489871589"
    },
    {
      "ref": "BomRef.062012191817703344.49266122826585734"
    },
    {
      "ref": "BomRef.6116128301474562.5137638303318507"
    },
    {
      "ref": "BomRef.8205015268929786.183534747464705"
    },
    {
      "ref": "BomRef.7674203601626399.9727872167600088"
    },
    {
      "ref": "BomRef.07254756197213386.8921284996085548"
    },
    {
      "ref": "BomRef.787705607814047.1434286330258584"
    },
    {
      "ref": "BomRef.36461515723031634.293704901061269"
    },
    {
      "ref": "BomRef.5953159827034046.7822423402553327"
    },
    {
      "ref": "BomRef.3646529792904001.5241600812988473"
    },
    {
      "ref": "BomRef.49466594038274503.1309141083579034"
    },
    {
      "ref": "BomRef.6836486802262614.25751389504214217"
    },
    {
      "ref": "BomRef.6150835749142108.2381819414441554"
    },
    {
      "ref": "BomRef.09413730679177457.4453167340081914"
    },
    {
      "ref": "BomRef.9618140028265427.2169137474651106"
    },
    {
      "ref": "BomRef.24210165143682427.9108332345109941"
    },
    {
      "ref": "BomRef.47124791204602146.022754232683465214"
    },
    {
      "ref": "BomRef.8741829368758849.814930948589656"
    },
    {
      "ref": "BomRef.858489408490906.8276266839955646"
    },
    {
      "ref": "BomRef.06004104628966789.7771052277891227"
    },
    {
      "ref": "BomRef.5446205429261812.25444310735587283"
    },
    {
      "ref": "BomRef.7029648021955753.14255122510509988"
    },
    {
      "ref": "BomRef.8860082289666387.5848918898529945"
    },
    {
      "ref": "BomRef.4937757936815731.18289289591076663"
    },
    {
      "ref": "BomRef.11171634813927067.82634141896032"
    },
    {
      "ref": "BomRef.5846763080850081.1625501928426374"
    },
    {
      "ref": "BomRef.866456653526203.3383387341769639"
    },
    {
      "ref": "BomRef.9486471790935657.4507243341174476"
    },
    {
      "ref": "BomRef.5728937023185666.38834239825823647"
    },
    {
      "ref": "BomRef.5653505824121918.790616916094003"
    },
    {
      "ref": "BomRef.20573920132313772.045865452663179984"
    },
    {
      "ref": "BomRef.6153753672433462.3422356156836608"
    },
    {
      "ref": "BomRef.8573261232617271.9688087109544156"
    },
    {
      "ref": "BomRef.24420921802104023.1381599731786386"
    },
    {
      "ref": "BomRef.7029191718117426.7209543357355848"
    },
    {
      "ref": "BomRef.24490850502155437.3040958434951938"
    },
    {
      "ref": "BomRef.5090672853874949.16367635762569388"
    },
    {
      "ref": "BomRef.17746955210333426.5749307672306114"
    },
    {
      "ref": "BomRef.22438930016266323.43826084523368014"
    },
    {
      "ref": "BomRef.7477949854509315.6201581286294816"
    },
    {
      "ref": "BomRef.27386252363697694.847335820761125"
    },
    {
      "ref": "BomRef.1693092195767828.019978008897911237"
    },
    {
      "ref": "BomRef.18674425310107823.35173353574053123"
    },
    {
      "ref": "BomRef.08215801946931423.6589235676874919"
    },
    {
      "ref": "BomRef.9964725481371729.7597031503293974"
    },
    {
      "ref": "BomRef.8227145822190692.0592663437373141"
    },
    {
      "ref": "BomRef.7934058889047312.37028885631583064"
    },
    {
      "ref": "BomRef.9444124999510763.9457027069583186"
    },
    {
      "ref": "BomRef.5329346635326255.31705414342563387"
    },
    {
      "ref": "BomRef.5366295419133734.6873977434381618"
    },
    {
      "ref": "BomRef.1513977447794428.8389650225127179"
    },
    {
      "ref": "BomRef.5469124038901767.4473383928224298"
    },
    {
      "ref": "BomRef.10938756009552597.3300926576881079"
    },
    {
      "ref": "BomRef.06646288548750612.07838253227117487"
    },
    {
      "ref": "BomRef.9445395981460681.608128563656574"
    },
    {
      "ref": "BomRef.8217329453660381.8165448139837509"
    },
    {
      "ref": "BomRef.24260073883923405.546150904731525"
    },
    {
      "ref": "BomRef.4874455545363099.11617780514507492"
    },
    {
      "ref": "BomRef.15616968553881716.7404580637378142"
    },
    {
      "ref": "BomRef.015251285026084083.5726410217003062"
    },
    {
      "ref": "BomRef.717600150965402.4877125536037026"
    },
    {
      "ref": "BomRef.32595213010467894.06452079515891507"
    },
    {
      "ref": "BomRef.44007338279434693.4187647255009058"
    },
    {
      "ref": "BomRef.8322828539792391.6127615308386836"
    },
    {
      "ref": "BomRef.932244932007372.5094787502399755"
    },
    {
      "ref": "BomRef.5132157465737628.11295308206024446"
    },
    {
      "ref": "BomRef.6594620275851222.05320409431023021"
    },
    {
      "ref": "BomRef.911844940654492.26190724416344946"
    },
    {
      "ref": "BomRef.15176843369108717.2893853154979652"
    },
    {
      "ref": "BomRef.28372242487914245.13604827176414314"
    },
    {
      "ref": "BomRef.27662145177673214.12674095952041053"
    },
    {
      "ref": "BomRef.2546109420421333.6392284422259783"
    },
    {
      "ref": "BomRef.4388463302713367.970790864615222"
    },
    {
      "ref": "BomRef.10430400278672225.24309525057334458"
    },
    {
      "ref": "BomRef.48712102028002324.4129004970298864"
    },
    {
      "ref": "BomRef.2976489159076232.4208212013443531"
    },
    {
      "ref": "BomRef.782229008402026.14648781281129208"
    },
    {
      "ref": "BomRef.8311951174030063.79694477790273"
    },
    {
      "ref": "BomRef.882540142010189.6294100739401446"
    },
    {
      "ref": "BomRef.5708818034221129.3804378761299618"
    },
    {
      "ref": "BomRef.36652782843032217.6956634453410063"
    },
    {
      "ref": "BomRef.3570620169721105.8971833638785001"
    },
    {
      "ref": "BomRef.2829694193449187.5877812480589429"
    },
    {
      "ref": "BomRef.27794806826922025.017531516503773492"
    },
    {
      "ref": "BomRef.5447581939640517.3470870648769323"
    },
    {
      "ref": "BomRef.11543822035669848.3931458759652209"
    },
    {
      "ref": "BomRef.9957289304301511.4949770751840835"
    },
    {
      "ref": "BomRef.31180001514978517.7973680439293804"
    },
    {
      "ref": "BomRef.8322931822907467.37110848756323567"
    },
    {
      "ref": "BomRef.6143491786106843.362568875709669"
    },
    {
      "ref": "BomRef.024488909026581185.11597685871456509"
    },
    {
      "ref": "BomRef.11250165345723151.13485070872451732"
    },
    {
      "ref": "BomRef.5775894136360654.035001192284008886"
    },
    {
      "ref": "BomRef.8515599379047767.9726387072919376"
    },
    {
      "ref": "BomRef.8698514761143893.8621563258245687"
    },
    {
      "ref": "BomRef.4965980667130342.39786641976415993"
    },
    {
      "ref": "BomRef.02706650076238104.07618723052387566"
    },
    {
      "ref": "BomRef.7078952103248536.4496411390556796"
    },
    {
      "ref": "BomRef.32212116970437266.2048772958802848"
    },
    {
      "ref": "BomRef.47376881244372615.3717763174675781"
    },
    {
      "ref": "BomRef.2923854921258543.044934131235749075"
    },
    {
      "ref": "BomRef.7070597787255379.510726977241715"
    },
    {
      "ref": "BomRef.4474208402550103.03802882293588217"
    },
    {
      "ref": "BomRef.4029864809446252.09458249273216346"
    },
    {
      "ref": "BomRef.01605595800528392.6997718836969521"
    },
    {
      "ref": "BomRef.6714605925232229.7543284928796826"
    },
    {
      "ref": "BomRef.9630967861977339.09678278006981433"
    },
    {
      "ref": "BomRef.5052613655781848.7341701481672441"
    },
    {
      "ref": "BomRef.9707614144704962.9115148897213815"
    },
    {
      "ref": "BomRef.17911703593542094.4655116816093825"
    },
    {
      "ref": "BomRef.8863867725004482.8531947056724442"
    },
    {
      "ref": "BomRef.5767953029467596.010556248392962653"
    },
    {
      "ref": "BomRef.832428181245846.9797654147548439"
    },
    {
      "ref": "BomRef.5018513199607161.3337204841226755"
    },
    {
      "ref": "BomRef.3448349710249058.4123611222269188"
    },
    {
      "ref": "BomRef.945734397771488.7891064872735736"
    },
    {
      "ref": "BomRef.4829884291936871.7123644307401936"
    },
    {
      "ref": "BomRef.504704650313748.12256129801796811"
    },
    {
      "ref": "BomRef.4884427677844084.6103957282605341"
    },
    {
      "ref": "BomRef.9283132601079156.03505387149439532"
    },
    {
      "ref": "BomRef.5622834153885823.48318763443828383"
    },
    {
      "ref": "BomRef.32351517968295407.9140654815918946"
    },
    {
      "ref": "BomRef.647282982919074.00907478953549945"
    },
    {
      "ref": "BomRef.5276356143626476.4172493114038509"
    },
    {
      "ref": "BomRef.37427670808859614.02560288929351251"
    },
    {
      "ref": "BomRef.3477760215057234.8986338458249457"
    },
    {
      "ref": "BomRef.4671208111214331.8880812726504487"
    },
    {
      "ref": "BomRef.48603254202922586.9644438314022694"
    },
    {
      "ref": "BomRef.1229956186282668.5103842095418231"
    },
    {
      "ref": "BomRef.4414008163725943.6238573278148198"
    },
    {
      "ref": "BomRef.8223702396343866.46828330007693497"
    },
    {
      "ref": "BomRef.1659020288322307.2157473419232776"
    },
    {
      "ref": "BomRef.799883482545087.7631765886229174"
    },
    {
      "ref": "pkg:oci/centos@centos7?digest=sha256:be65f488b7764ad3638f236b7b515b3678369a5124c47b8d32916d6487418ea4",
      "dependsOn": [
        "BomRef.057993642585890015.8648595561273664",
        "BomRef.8319671758737434.3874282118419835",
        "BomRef.9105788447659425.5903817558848735",
        "BomRef.3324682176988484.6116024106049724",
        "BomRef.8006393402239098.4666929798988605",
        "BomRef.7643075368628234.394384352153599",
        "BomRef.4048789714699442.3605213520615854",
        "BomRef.3821354631203039.10719869032732732",
        "BomRef.9474213003526996.752763757863455",
        "BomRef.8406906183661705.17813406204012705",
        "BomRef.8913192243643914.2562558584536698",
        "BomRef.00220718568002376.9400253389255641",
        "BomRef.33684947783861263.012520512779695347",
        "BomRef.07738674078897034.5919048846959302",
        "BomRef.7102766486771992.49653558115444096",
        "BomRef.7000002960800513.8576172039618027",
        "BomRef.7939819540278187.5418607342190763",
        "BomRef.7869926598497546.018128985081250604",
        "BomRef.8128886103442383.8369284112703149",
        "BomRef.046201384183194416.7153972558318439",
        "BomRef.6266479496990721.6755247596276939",
        "BomRef.09646571441629337.15215251842763444",
        "BomRef.2177583145952482.2085145602198637",
        "BomRef.44172163091307226.4004541134644547",
        "BomRef.15076870899981953.6633781319342072",
        "BomRef.36209744185831294.8138358372671167",
        "BomRef.3026323107558184.06681851290715468",
        "BomRef.24874492921958002.6899724220523172",
        "BomRef.46902099014219756.6491639247271938",
        "BomRef.8667189490557057.3290089063513786",
        "BomRef.7444794338435629.2577597325025265",
        "BomRef.6862769621447209.967507930635375",
        "BomRef.3784304008894782.5118519880466966",
        "BomRef.04053329806906536.42725921623339147",
        "BomRef.38197213244674333.38584593667802947",
        "BomRef.8126181861988361.41434738507603197",
        "BomRef.1535708737125726.9851514921168668",
        "BomRef.7409536391314157.6831896820525055",
        "BomRef.3566743278951017.7022088814409161",
        "BomRef.6610941716539932.2687495826670516",
        "BomRef.9012058949879385.8642435859541833",
        "BomRef.7134131471678684.7889429814817616",
        "BomRef.6218149150985431.3039539087537433",
        "BomRef.8887838325397045.9350095567880532",
        "BomRef.30571853313711084.4460882537765475",
        "BomRef.3934545941634071.08345323379101399",
        "BomRef.6194425528485259.33842079640205003",
        "BomRef.6241981551378307.24462842266975637",
        "BomRef.6249323781848204.2800542636206207",
        "BomRef.3585567576707819.9319653832146283",
        "BomRef.6332229786811459.8819197214733189",
        "BomRef.6063912485771416.312914175475967",
        "BomRef.4888581320832842.3539499570520953",
        "BomRef.4578503510904596.6764302156482087",
        "BomRef.08841347830938262.9618312134939507",
        "BomRef.5798775058855651.7591171885782486",
        "BomRef.6031860677211648.3239693754658175",
        "BomRef.9449621915662985.18331485194585295",
        "BomRef.6547913237021074.33136721587494666",
        "BomRef.30890741493735263.44419363445007753",
        "BomRef.4555454864853925.41555854696678507",
        "BomRef.24519108893793717.11547544648482422",
        "BomRef.6684533381970013.1591904398140409",
        "BomRef.5542748180157804.3930952649308992",
        "BomRef.10978319758943689.9304933730628435",
        "BomRef.7029642512180814.5555895094100395",
        "BomRef.4189278993854423.6280345562612181",
        "BomRef.02183064099084342.566083058802005",
        "BomRef.886341185060498.7209855120228137",
        "BomRef.055281773534456735.8737068040330332",
        "BomRef.7895181935851667.018996242220371995",
        "BomRef.672049737170431.22326891358917367",
        "BomRef.14671596241459317.7706657957152158",
        "BomRef.4886027279476527.8228142696125779",
        "BomRef.5533104227868851.8033999424504054",
        "BomRef.8334891432288822.45795039089387823",
        "BomRef.989883659417556.9319636192227638",
        "BomRef.1280962955337872.6380582352989193",
        "BomRef.22038733579669623.4783478835232551",
        "BomRef.06471282000115353.6304173931237735",
        "BomRef.5010019553721136.5657988123749819",
        "BomRef.2705250193258294.18583844855572262",
        "BomRef.33857822218813316.7552305384093357",
        "BomRef.017430620072204417.844902489330875",
        "BomRef.814593152925056.31240117238564813",
        "BomRef.86510174762046.0036254408100384605",
        "BomRef.27164766798168016.2703144002373641",
        "BomRef.15810767743355147.6053859461320094",
        "BomRef.8800027629466532.5679214817870296",
        "BomRef.8557107532354669.7833104129870408",
        "BomRef.10248628051791409.5040119349763146",
        "BomRef.26407949568515654.6908314029997384",
        "BomRef.8789965874274014.0549419345103106",
        "BomRef.9312443860029734.5181854661024881",
        "BomRef.8856308642162309.861413307131058",
        "BomRef.6072262996782428.5145314283773903",
        "BomRef.9551234838225656.9213149137759589",
        "BomRef.6049781965275146.9126958622673069",
        "BomRef.1813946462367355.851964614086686",
        "BomRef.7250010128803137.2666620096170671",
        "BomRef.6715443298626859.6217813837827428",
        "BomRef.8482080066185224.10958285108431443",
        "BomRef.6229149125761952.5741970172408265",
        "BomRef.8959186262053416.8964785106518575",
        "BomRef.9170892163702018.5490025919519991",
        "BomRef.8296968833052679.34668572699676536",
        "BomRef.46502013186201085.9108923599354485",
        "BomRef.3498315774854065.16096734142206037",
        "BomRef.4533028365084485.9710242854146007",
        "BomRef.4790588771748582.6411225422428273",
        "BomRef.7410904425378922.8150480979104315",
        "BomRef.12634523382888185.16951539618005262",
        "BomRef.5674407609381681.022180079755491744",
        "BomRef.4806774059496499.355505218075278",
        "BomRef.06442741136731589.42460298589500156",
        "BomRef.47373043936031745.5694667143184716",
        "BomRef.4840460880463867.7868002074381268",
        "BomRef.6410873741070992.036857118978913195",
        "BomRef.6112987920128037.21125736682874563",
        "BomRef.013275730938444474.49747937250809626",
        "BomRef.8917237585569491.45259873943245654",
        "BomRef.663987839268528.04752075229213937",
        "BomRef.05398672634921997.7650355545711406",
        "BomRef.9458203765062017.9059459931882156",
        "BomRef.08668541373588312.1725346438705757",
        "BomRef.45487917549634593.4177623362994095",
        "BomRef.2370556436538903.22947977889555993",
        "BomRef.4959378946090258.8173692139455248",
        "BomRef.9543921988087452.7225843850150544",
        "BomRef.46538868473956774.8189112356011137",
        "BomRef.6238528413172444.19213442922506874",
        "BomRef.10942467001581924.08997947923827398",
        "BomRef.9335194056541933.6581218695457874",
        "BomRef.757285176615639.30079946128356727",
        "BomRef.9054974962289634.501556331610808",
        "BomRef.3392239156162711.20189195507214852",
        "BomRef.20525385563201737.0536643096858791",
        "BomRef.7111467413978058.506607624759521",
        "BomRef.0500009078605308.16525287386835474",
        "BomRef.07838849536073544.31005096468217097",
        "BomRef.47723996773660604.6749478586608814",
        "BomRef.15204947482051578.680892082236111",
        "BomRef.7603726149683712.44842367717705334",
        "BomRef.3195706808242019.7364347884236024",
        "BomRef.8697643274403607.9244141858229975",
        "BomRef.805817690117059.980527669909242",
        "BomRef.34765062897750365.22107471345725438",
        "BomRef.8427782588882277.3444399947044008",
        "BomRef.5066196666855471.3307682667796954",
        "BomRef.08414766719086875.8459684995663234"
      ]
    }
  ],
  "serialNumber": "urn:uuid:aa7720d7-e798-44de-a988-f3463f51860c"
}